edenpdf/__init__.py
edenpdf/file.py
edenpdf/ilovepdf.py
edenpdf/request.py
edenpdf/response.py
edenpdf/samples/compress.py
edenpdf/samples/compress_alternative.py
edenpdf/samples/imagetopdf.py
edenpdf/samples/merge.py
edenpdf/samples/officepdf.py
edenpdf/samples/pagenumber.py
edenpdf/samples/pdfa.py
edenpdf/samples/pdftojpg.py
edenpdf/samples/protect.py
edenpdf/samples/rotate.py
edenpdf/samples/split.py
edenpdf/samples/unlock.py
edenpdf/samples/validatepdfa.py
edenpdf/samples/watermark.py
edenpdf/task.py
edenpdf/tools/__init__.py
edenpdf/tools/compress.py
edenpdf/tools/imagetopdf.py
edenpdf/tools/merge.py
edenpdf/tools/officepdf.py
edenpdf/tools/pagenumber.py
edenpdf/tools/pdfa.py
edenpdf/tools/pdftojpg.py
edenpdf/tools/protect.py
edenpdf/tools/rotate.py
edenpdf/tools/split.py
edenpdf/tools/unlock.py
edenpdf/tools/validatepdfa.py
edenpdf/tools/watermark.py
edenpdf-1.0.3.dist-info/LICENSE.md
edenpdf-1.0.3.dist-info/WHEEL
edenpdf-1.0.3.dist-info/METADATA
edenpdf-1.0.3.dist-info/RECORD
