Metadata-Version: 2.1
Name: edenpdf
Version: 1.0.3
Summary: ilovepdf.com python API library
Home-page: https://github.com/eden-box/edenpdf
License: GPL-3.0-only
Keywords: pdf,unlock,compress,manipulate,edit,protect,pdftojpg,jpgtopdf,pdfa
Author: Eden-Box
Author-email: dev@edenbox.cf
Requires-Python: >=3.6.0,<4.0.0
Classifier: Development Status :: 5 - Production/Stable
Classifier: License :: OSI Approved :: GNU General Public License v3 (GPLv3)
Classifier: Programming Language :: Python :: 3
Classifier: Programming Language :: Python :: 3.6
Classifier: Programming Language :: Python :: 3.7
Classifier: Topic :: Software Development :: Libraries :: Python Modules
Requires-Dist: requests (>=2.22.0,<3.0.0)
Requires-Dist: urllib3 (>=1.25.0,<2.0.0)
Project-URL: Repository, https://github.com/eden-box/edenpdf
